logictools/__init__.py
logictools/math_utils.py
logictools/string_utils.py
logictools-2025.3.8.1708.dist-info/METADATA
logictools-2025.3.8.1708.dist-info/WHEEL
logictools-2025.3.8.1708.dist-info/RECORD
